workon_poetry/__init__.py
workon_poetry/constants.py
workon_poetry/data/pyproject.template.toml
workon_poetry-0.0.4.dist-info/METADATA
workon_poetry-0.0.4.dist-info/WHEEL
workon_poetry-0.0.4.dist-info/RECORD
