Metadata-Version: 2.1
Name: workon-poetry
Version: 0.0.4
Summary: Natural Language Understanding (text processing) for math symbols, digits, and words with a Gradio user interface and REST API.
Home-page: https://gitlab.com/tangibleai/community/workon-poetry
License: AGPL-3.0-or-later
Author: Hobson Lane
Author-email: gitlab@totalgood.com
Requires-Python: >=3.7
Classifier: License :: OSI Approved :: GNU Affero General Public License v3 or later (AGPLv3+)
Classifier: Operating System :: OS Independent
Classifier: Programming Language :: Python :: 3
Classifier: Programming Language :: Python :: 3.7
Classifier: Programming Language :: Python :: 3.8
Classifier: Programming Language :: Python :: 3.9
Classifier: Programming Language :: Python :: 3.10
Classifier: Programming Language :: Python :: 3.11
Classifier: Programming Language :: Python :: 3
Classifier: Programming Language :: Python :: 3.10
Classifier: Programming Language :: Python :: 3.7
Classifier: Programming Language :: Python :: 3.8
Classifier: Programming Language :: Python :: 3.9
Requires-Dist: pip (>=23.0)
Requires-Dist: poetry (>=1.0)
Requires-Dist: python-dotenv (>=0.21)
Requires-Dist: sentry_sdk
Requires-Dist: virtualenv (>=20.0,<21.0)
Project-URL: Repository, https://gitlab.com/tangibleai/community/workon-poetry
